embedding_generator/__init__.py
embedding_generator/generator.py
embedding_generator/limit_estimator.py
embedding_generator/token_counter.py
embedding_generator/utils.py
embedding_generator-0.1.0.dist-info/METADATA
embedding_generator-0.1.0.dist-info/WHEEL
embedding_generator-0.1.0.dist-info/RECORD
