Metadata-Version: 2.1
Name: embedding-generator
Version: 0.1.0
Summary: A module for generating embeddings for batches of texts using a SentenceTransformer model.
Home-page: https://github.com/rrhd/embeddingGenerator
License: MIT
Keywords: embedding,NLP,SentenceTransformer
Author: Ron Heichman
Author-email: ronheichman@gmail.com
Requires-Python: >=3.8,<4.0
Classifier: License :: OSI Approved :: MIT License
Classifier: Programming Language :: Python :: 3
Classifier: Programming Language :: Python :: 3.8
Classifier: Programming Language :: Python :: 3.9
Classifier: Programming Language :: Python :: 3.10
Classifier: Programming Language :: Python :: 3.11
Classifier: Programming Language :: Python :: 3.12
Requires-Dist: langchain_text_splitters (>=0.1,<0.2)
Requires-Dist: numpy (>=1.21,<2.0)
Requires-Dist: orjson (>=3.6,<4.0)
Requires-Dist: psutil (>=5.8,<6.0)
Requires-Dist: sentence-transformers (>=2.0,<3.0)
Requires-Dist: torch (>=1.9,<2.0)
Requires-Dist: tqdm (>=4.61,<5.0)
Project-URL: Repository, https://github.com/rrhd/embeddingGenerator
